{"cameraMode":{"drawMode":0,"name":"Shaded","section":"Shading Mode"},"sceneLighting":true,"audioPlay":false,"sceneViewState":{"m_AlwaysRefresh":false,"showFog":true,"showSkybox":true,"showFlares":true,"showImageEffects":true,"showParticleSystems":true,"showVisualEffectGraphs":true,"m_FxEnabled":true},"in2DMode":false,"pivot":{"x":1.9892032146453858,"y":1.096562385559082,"z":0.40664470195770266},"rotation":{"x":-0.09037616848945618,"y":-0.9073581695556641,"z":0.256510853767395,"w":-0.3209116756916046},"size":0.1579750031232834,"orthographic":false}